KerasTutorialsTgjeon/README.md
KerasTutorialsTgjeon/__init__.py
KerasTutorialsTgjeon/__main__.py
KerasTutorialsTgjeon/file.epub
KerasTutorialsTgjeon/index.html
KerasTutorialsTgjeon/css/__init__.py
KerasTutorialsTgjeon/css/annotations.css
KerasTutorialsTgjeon/css/main.css
KerasTutorialsTgjeon/css/normalize.css
KerasTutorialsTgjeon/css/popup.css
KerasTutorialsTgjeon/font/__init__.py
KerasTutorialsTgjeon/font/fontello.eot
KerasTutorialsTgjeon/font/fontello.svg
KerasTutorialsTgjeon/font/fontello.ttf
KerasTutorialsTgjeon/font/fontello.woff
KerasTutorialsTgjeon/img/__init__.py
KerasTutorialsTgjeon/img/annotator-glyph-sprite.png
KerasTutorialsTgjeon/img/annotator-icon-sprite.png
KerasTutorialsTgjeon/img/apple-touch-icon.png
KerasTutorialsTgjeon/img/cancelfullscreen.png
KerasTutorialsTgjeon/img/close.png
KerasTutorialsTgjeon/img/fullscreen.png
KerasTutorialsTgjeon/img/loader.gif
KerasTutorialsTgjeon/img/menu-icon.png
KerasTutorialsTgjeon/img/save.png
KerasTutorialsTgjeon/img/saved.png
KerasTutorialsTgjeon/img/settings-s.png
KerasTutorialsTgjeon/img/settings.png
KerasTutorialsTgjeon/img/star.png
KerasTutorialsTgjeon/js/__init__.py
KerasTutorialsTgjeon/js/epub.js
KerasTutorialsTgjeon/js/epub.min.js
KerasTutorialsTgjeon/js/epub.min.map
KerasTutorialsTgjeon/js/hooks.min.js
KerasTutorialsTgjeon/js/hooks.min.map
KerasTutorialsTgjeon/js/reader.js
KerasTutorialsTgjeon/js/reader.js.map
KerasTutorialsTgjeon/js/reader.min.js
KerasTutorialsTgjeon/js/reader.min.map
KerasTutorialsTgjeon/js/hooks/__init__.py
KerasTutorialsTgjeon/js/hooks/extensions/__init__.py
KerasTutorialsTgjeon/js/hooks/extensions/highlight.js
KerasTutorialsTgjeon/js/libs/__init__.py
KerasTutorialsTgjeon/js/libs/jquery.min.js
KerasTutorialsTgjeon/js/libs/localforage.min.js
KerasTutorialsTgjeon/js/libs/screenfull.js
KerasTutorialsTgjeon/js/libs/screenfull.min.js
KerasTutorialsTgjeon/js/libs/zip.min.js
KerasTutorialsTgjeon/js/plugins/__init__.py
KerasTutorialsTgjeon/js/plugins/hypothesis.js
keras_tutorials_tgjeon-2024.3.5.0.dist-info/METADATA
keras_tutorials_tgjeon-2024.3.5.0.dist-info/WHEEL
keras_tutorials_tgjeon-2024.3.5.0.dist-info/entry_points.txt
keras_tutorials_tgjeon-2024.3.5.0.dist-info/top_level.txt
keras_tutorials_tgjeon-2024.3.5.0.dist-info/RECORD
